data_loader_plugin/__init__.py
data_loader_plugin/base.py
data_loader_plugin/copyfile.py
data_loader_plugin/s3.py
tests/__init__.py
tests/test_copyfile.py
tests/test_s3.py
data_loader_plugin-0.0.1.post1.dist-info/LICENSE
data_loader_plugin-0.0.1.post1.dist-info/METADATA
data_loader_plugin-0.0.1.post1.dist-info/WHEEL
data_loader_plugin-0.0.1.post1.dist-info/top_level.txt
data_loader_plugin-0.0.1.post1.dist-info/RECORD
