Metadata-Version: 2.1
Name: data-loader-plugin
Version: 0.0.1.post1
Summary: Python plugin/extra to load data files from an external source (such as AWS S3) to a local directory
Home-page: https://github.com/cloud-helpers/python-plugin-data-loader
Author: Stanislav Khrapov
Author-email: khrapovs@gmail.com
License: MIT
Project-URL: Documentation, https://github.com/cloud-helpers/python-plugin-data-loader
Project-URL: Issue Tracker, https://github.com/cloud-helpers/python-plugin-data-loader/issues
Keywords: data,machine-learning,data-loader,ml
Platform: UNKNOWN
Classifier: Development Status :: 5 - Production/Stable
Classifier: Intended Audience :: Developers
Classifier: License :: OSI Approved :: MIT License
Classifier: Operating System :: Unix
Classifier: Operating System :: POSIX
Classifier: Operating System :: Microsoft :: Windows
Classifier: Programming Language :: Python
Classifier: Programming Language :: Python :: 3
Classifier: Programming Language :: Python :: 3.6
Classifier: Programming Language :: Python :: 3.7
Classifier: Programming Language :: Python :: 3.8
Classifier: Programming Language :: Python :: 3.9
Classifier: Programming Language :: Python :: 3.10
Classifier: Topic :: Utilities
Requires-Python: >=2.7, !=3.0.*, !=3.1.*, !=3.2.*, !=3.3.*, !=3.4.*, !=3.5.*
License-File: LICENSE
Requires-Dist: boto3
